[
    {
        "id": "12"
    },
    {
        "id": "10"
    },
    {
        "id": "9"
    },
    {
        "id": "13"
    },
    {
        "id": "7"
    },
    {
        "id": "8"
    },
    {
        "id": "6"
    },
    {
        "id": "16"
    },
    {
        "id": "18"
    },
    {
        "id": "19"
    },
    {
        "id": "13"
    },
    {
        "id": "14"
    },
    {
        "id": "4"
    },
    {
        "id": "7"
    },
    {
        "id": "6"
    },
    {
        "id": "12"
    },
    {
        "id": "11"
    }
]