{
    "id": 1,
    "children": [
        {
            "id": 2,
            "children": [
                {
                    "id": 3,
                    "info": {
                        "Relative_Type_Mean": 1.005,
                        "Pop_Share": 29.25,
                        "Box_Number": 3
                    },
                    "split_condition": "Father_Edu -> No Schooling,Elementary School,High School"
                },
                {
                    "id": 4,
                    "children": [
                        {
                            "id": 5,
                            "children": [
                                {
                                    "id": 6,
                                    "info": {
                                        "Relative_Type_Mean": 1.333,
                                        "Pop_Share": 1.52,
                                        "Box_Number": 6
                                    },
                                    "split_condition": "Birth_Area -> Seoul,Daegu,Daejeon,Gwangju,Ulsan,Gyeonggi-Do,Jeollanam-Do,Jeju-Do"
                                },
                                {
                                    "id": 7,
                                    "info": {
                                        "Relative_Type_Mean": 1.323,
                                        "Pop_Share": 1.78,
                                        "Box_Number": 7
                                    },
                                    "split_condition": "Birth_Area -> Busan,Incheon,Gangwon-Do,Chungcheongbuk-Do,Chungcheongnam-Do,Jeollabuk-Do,Gyeongsangbuk-Do,Gyeonsangnam-Do,North Korea,Overseas"
                                }
                            ],
                            "nodeName": "Birth_Area",
                            "split_condition": "Father_Edu -> Middle School,Graduate Degree"
                        },
                        {
                            "id": 8,
                            "info": {
                                "Relative_Type_Mean": 1.07,
                                "Pop_Share": 4.8,
                                "Box_Number": 8
                            },
                            "split_condition": "Father_Edu -> Community College,College/University"
                        }
                    ],
                    "nodeName": "Father_Edu",
                    "split_condition": "Father_Edu -> Middle School,Community College,College/University,Graduate Degree"
                }
            ],
            "nodeName": "Father_Edu",
            "split_condition": "Mother_Edu -> No Schooling,Community College,College/University,Graduate Degree"
        },
        {
            "id": 9,
            "children": [
                {
                    "id": 10,
                    "info": {
                        "Relative_Type_Mean": 0.915,
                        "Pop_Share": 35.56,
                        "Box_Number": 10
                    },
                    "split_condition": "Birth_Area -> Seoul,Busan,Daegu,Gyeonggi-Do,Gangwon-Do,Gyeongsangbuk-Do,Overseas"
                },
                {
                    "id": 11,
                    "children": [
                        {
                            "id": 12,
                            "info": {
                                "Relative_Type_Mean": 1.126,
                                "Pop_Share": 11.68,
                                "Box_Number": 12
                            },
                            "split_condition": "Father_Occ -> Regular/Standard Wage Worker,Employer (With Employees)"
                        },
                        {
                            "id": 13,
                            "children": [
                                {
                                    "id": 14,
                                    "info": {
                                        "Relative_Type_Mean": 0.963,
                                        "Pop_Share": 12.29,
                                        "Box_Number": 14
                                    },
                                    "split_condition": "Ethnicity -> None,Protestant,Won Buddhist,Other"
                                },
                                {
                                    "id": 15,
                                    "info": {
                                        "Relative_Type_Mean": 1.074,
                                        "Pop_Share": 3.13,
                                        "Box_Number": 15
                                    },
                                    "split_condition": "Ethnicity -> Buddhist,Catholic,Chondo Faith"
                                }
                            ],
                            "nodeName": "Ethnicity",
                            "split_condition": "Father_Occ -> Irregular/Nonstandard Wage Worker,Self-Employed(With No Employee),Family Worker,No Job/Housewife"
                        }
                    ],
                    "nodeName": "Father_Occ",
                    "split_condition": "Birth_Area -> Daejeon,Incheon,Gwangju,Ulsan,Chungcheongbuk-Do,Chungcheongnam-Do,Jeollabuk-Do,Jeollanam-Do,Gyeonsangnam-Do,Jeju-Do,North Korea"
                }
            ],
            "nodeName": "Birth_Area",
            "split_condition": "Mother_Edu -> Elementary School,Middle School,High School"
        }
    ],
    "nodeName": "Mother_Edu"
}